vr/__init__.py
vr/common/__init__.py
vr/common/models.py
vr/common/paths.py
vr/common/repo.py
vr/common/slugignore.py
vr/common/utils.py
vr/common/balancer/__init__.py
vr/common/balancer/base.py
vr/common/balancer/chained.py
vr/common/balancer/dummy.py
vr/common/balancer/nginx.py
vr/common/balancer/stingray.py
vr/common/balancer/stingray_pool.wsdl
vr/common/balancer/varnish.py
vr/common/templates/precise.lxc
vr/common/templates/proc.conf
vr/common/templates/proc.sh
vr/common/templates/start_proc.sh
vr/common/tests/__init__.py
vr/common/tests/buildpack_hello.tar.gz
vr/common/tests/git_python_app.tar.gz
vr/common/tests/hg_python_app.tar.gz
vr/common/tests/test_models.py
vr/common/tests/test_repos.py
vr/common/tests/test_utils.py
vr.common-6.1.1.dist-info/LICENSE
vr.common-6.1.1.dist-info/METADATA
vr.common-6.1.1.dist-info/WHEEL
vr.common-6.1.1.dist-info/top_level.txt
vr.common-6.1.1.dist-info/RECORD
